qspool.py
qspool-0.5.0.dist-info/LICENSE
qspool-0.5.0.dist-info/METADATA
qspool-0.5.0.dist-info/WHEEL
qspool-0.5.0.dist-info/top_level.txt
qspool-0.5.0.dist-info/RECORD
