Metadata-Version: 2.1
Name: qspool
Version: 0.5.0
Summary: Dependency-free script to spool jobs into SLURM scheduler without exceeding queue capacity limits.
Author-email: Matthew Andres Moreno <m.more500@gmail.com>
License: MIT license
Project-URL: homepage, https://github.com/mmore500/qspool
Keywords: slurm,high-performance computing,cluster computing
Classifier: Development Status :: 4 - Beta
Classifier: Intended Audience :: Developers
Classifier: Operating System :: OS Independent
Classifier: Programming Language :: Python :: 3
Classifier: License :: OSI Approved :: MIT License
Classifier: Topic :: Software Development :: Libraries :: Python Modules
Requires-Python: >=3.6
License-File: LICENSE
